pypsql_api/__init__.py
pypsql_api/config/__init__.py
pypsql_api/config/types.py
pypsql_api/context.py
pypsql_api/ext/__init__.py
pypsql_api/ext/handlers.py
pypsql_api/server.py
pypsql_api/wire/__init__.py
pypsql_api/wire/actions.py
pypsql_api/wire/actions_types.py
pypsql_api/wire/back.py
pypsql_api/wire/bytes.py
pypsql_api/wire/dataframe/types.py
pypsql_api/wire/errors/__init__.py
pypsql_api/wire/errors/core.py
pypsql_api/wire/extended/__init__.py
pypsql_api/wire/extended/types.py
pypsql_api/wire/front.py
pypsql_api/wire/protocol.py
pypsql_api/wire/query/__init__.py
pypsql_api/wire/query/extended_query.py
pypsql_api/wire/query/simple_query.py
pypsql_api-0.2.5.dist-info/LICENSE
pypsql_api-0.2.5.dist-info/WHEEL
pypsql_api-0.2.5.dist-info/METADATA
pypsql_api-0.2.5.dist-info/RECORD
